markdownizer/__init__.py
markdownizer/admonition.py
markdownizer/basesection.py
markdownizer/classhelpers.py
markdownizer/docs.py
markdownizer/docstrings.py
markdownizer/document.py
markdownizer/image.py
markdownizer/list.py
markdownizer/mermaid.py
markdownizer/mermaiddiagram.py
markdownizer/nav.py
markdownizer/node.py
markdownizer/table.py
markdownizer/utils.py
markdownizer-0.0.1.dist-info/METADATA
markdownizer-0.0.1.dist-info/WHEEL
markdownizer-0.0.1.dist-info/entry_points.txt
markdownizer-0.0.1.dist-info/licenses/LICENSE
markdownizer-0.0.1.dist-info/RECORD
