Metadata-Version: 2.1
Name: markdownizer
Version: 0.0.1
Summary: Generate docs with ease.
Project-URL: Documentation, https://phil65.github.io/markdownizer/
Project-URL: Source, https://github.com/phil65/markdownizer
Author-email: markdownizer <philipptemminghoff@gmail.com>
License-File: LICENSE
Classifier: Programming Language :: Python :: 3 :: Only
Requires-Python: >=3.10
